mate_cli/__init__.py
mate_cli/cli.py
mate_cli-0.0.1.dist-info/METADATA
mate_cli-0.0.1.dist-info/WHEEL
mate_cli-0.0.1.dist-info/entry_points.txt
mate_cli-0.0.1.dist-info/top_level.txt
mate_cli-0.0.1.dist-info/RECORD
