Metadata-Version: 2.1
Name: mate-cli
Version: 0.0.1
Summary: A CLI for the MATE REST API
Author: The MATE authors
Author-email: mate@galois.com
License: BSD-3-Clause
Project-URL: Documentation, https://mate.galois.com
Platform: any
Requires-Python: >=3.8
Requires-Dist: halo (==0.0.31)
Requires-Dist: pydantic (~=1.9.0)
Requires-Dist: mate-common
Requires-Dist: mate-rest-client
